README.rst
indexed_list.py
setup.py
indexed_list.egg-info/PKG-INFO
indexed_list.egg-info/SOURCES.txt
indexed_list.egg-info/dependency_links.txt
indexed_list.egg-info/top_level.txt