Metadata-Version: 1.1
Name: indexed-list
Version: 0.1.0
Summary: Indexed list and table datatypes
Home-page: UNKNOWN
Author: Szymon Pyżalski
Author-email: szymon@pythonista.net
License: UNKNOWN
Platform: UNKNOWN
Classifier: Development Status :: 3 - Alpha
Classifier: Intended Audience :: Developers
Classifier: License :: OSI Approved :: BSD License
Classifier: Programming Language :: Python :: 3.3
Classifier: Topic :: Software Development :: Libraries :: Python Modules
